{
  "main": {
    "id": "main-workspace",
    "type": "split",
    "children": [
      {
        "id": "6334616a477755ff",
        "type": "tabs",
        "children": [
          {
            "id": "editor",
            "type": "leaf",
            "state": {
              "type": "markdown",
              "state": {
                "file": "Sync Log.md",
                "mode": "source",
                "source": false
              },
              "icon": "lucide-file",
              "title": "Sync Log"
            }
          }
        ]
      }
    ],
    "direction": "vertical"
  },
  "left": {
    "id": "left-sidebar",
    "type": "split",
    "children": [
      {
        "id": "31c939399df37236",
        "type": "tabs",
        "children": [
          {
            "id": "59ac0d8ef79d3bbc",
            "type": "leaf",
            "state": {
              "type": "search",
              "state": {
                "query": "",
                "matchingCase": false,
                "explainSearch": false,
                "collapseAll": false,
                "extraContext": false,
                "sortOrder": "alphabetical"
              },
              "icon": "lucide-search",
              "title": "Search"
            }
          },
          {
            "id": "09e2b63d04e5f3c0",
            "type": "leaf",
            "state": {
              "type": "bookmarks",
              "state": {},
              "icon": "lucide-bookmark",
              "title": "Bookmarks"
            }
          },
          {
            "id": "file-explorer",
            "type": "leaf",
            "state": {
              "type": "file-explorer",
              "state": {
                "sortOrder": "alphabetical",
                "autoReveal": false
              },
              "icon": "lucide-folder-closed",
              "title": "Files"
            }
          }
        ],
        "currentTab": 2
      }
    ],
    "direction": "horizontal",
    "width": 300
  },
  "right": {
    "id": "right-sidebar",
    "type": "split",
    "children": [
      {
        "id": "678a4881236b8d27",
        "type": "tabs",
        "children": [
          {
            "id": "d2816deb632c84c3",
            "type": "leaf",
            "state": {
              "type": "backlink",
              "state": {
                "file": "README.md",
                "collapseAll": false,
                "extraContext": false,
                "sortOrder": "alphabetical",
                "showSearch": false,
                "searchQuery": "",
                "backlinkCollapsed": false,
                "unlinkedCollapsed": true
              },
              "icon": "links-coming-in",
              "title": "Backlinks for README"
            }
          },
          {
            "id": "f8d3987f20ce9b0f",
            "type": "leaf",
            "state": {
              "type": "all-properties",
              "state": {
                "sortOrder": "frequency",
                "showSearch": false,
                "searchQuery": ""
              },
              "icon": "lucide-archive",
              "title": "All properties"
            }
          }
        ]
      }
    ],
    "direction": "horizontal",
    "width": 300,
    "collapsed": true
  },
  "left-ribbon": {
    "hiddenItems": {
      "switcher:Open quick switcher": false,
      "graph:Open graph view": false,
      "canvas:Create new canvas": false,
      "command-palette:Open command palette": false,
      "markdown-importer:Open format converter": false,
      "bases:Create new base": false,
      "obsidian-p2p-sync:P2P Sync": false
    }
  },
  "active": "editor",
  "lastOpenFiles": [
    "Device A Notes.md",
    "Device B Notes.md",
    "README.md"
  ]
}